{
    "王毅": {
        "org": "中国外交部部长",
        "weight": 10
    },
    "华春莹": {
        "org": "中国外交部发言人",
        "weight": 8
    },
    "蓬佩奥": {
        "org": "美国国务卿",
        "weight": 8
    },
    "吴谦": {
        "org": "中国国防部发言人",
        "weight": 10
    },
    "洪磊": {
        "org": "中国外交部发言人",
        "weight": 8
    },
    "汪文斌": {
        "org": "中国外交部发言人",
        "weight": 8
    },
    "李华敏": {
        "org": "中国人民解放军南部战区新闻发言人",
        "weight": 8
    },
    "任国强":{
        "org": "中国国防部新闻发言人",
        "weight": 9    
    }

 
}